accessible_output2/__init__.py
accessible_output2/ao2.py
accessible_output2/__pyinstaller/__init__.py
accessible_output2/__pyinstaller/hook-accessible_output2.py
accessible_output2/lib/PCTKUSR.dll
accessible_output2/lib/PCTKUSR64.dll
accessible_output2/lib/SAAPI32.dll
accessible_output2/lib/dolapi.dll
accessible_output2/lib/nvdaControllerClient32.dll
accessible_output2/lib/nvdaControllerClient64.dll
accessible_output2/outputs/__init__.py
accessible_output2/outputs/auto.py
accessible_output2/outputs/base.py
accessible_output2/outputs/dolphin.py
accessible_output2/outputs/e_speak.py
accessible_output2/outputs/jaws.py
accessible_output2/outputs/nvda.py
accessible_output2/outputs/pc_talker.py
accessible_output2/outputs/sapi4.py
accessible_output2/outputs/sapi5.py
accessible_output2/outputs/system_access.py
accessible_output2/outputs/voiceover.py
accessible_output2/outputs/window_eyes.py
bp_accessible_output2-0.6.dist-info/METADATA
bp_accessible_output2-0.6.dist-info/WHEEL
bp_accessible_output2-0.6.dist-info/entry_points.txt
bp_accessible_output2-0.6.dist-info/top_level.txt
bp_accessible_output2-0.6.dist-info/RECORD
